shinymap/__init__.py
shinymap/_aesthetics.py
shinymap/_base.py
shinymap/_sentinel.py
shinymap/_theme.py
shinymap/_ui.py
shinymap/_validation.py
shinymap/_wash.py
shinymap/aes.py
shinymap/linestyle.py
shinymap/mode.py
shinymap/relative.py
shinymap/color/__init__.py
shinymap/color/binary.py
shinymap/color/cycle.py
shinymap/color/neutral.py
shinymap/color/qualitative.py
shinymap/color/scale.py
shinymap/color/sequential.py
shinymap/geometry/__init__.py
shinymap/geometry/_bounds.py
shinymap/geometry/_conversion.py
shinymap/geometry/_core.py
shinymap/geometry/_element_mixins.py
shinymap/geometry/_elements.py
shinymap/geometry/_export.py
shinymap/geometry/_geometry.py
shinymap/geometry/_loader.py
shinymap/geometry/_regions.py
shinymap/geometry/_repr_config.py
shinymap/geometry/converter/README.md
shinymap/geometry/converter/__init__.py
shinymap/geometry/converter/__main__.py
shinymap/geometry/converter/_app.py
shinymap/geometry/converter/_tool.py
shinymap/utils/__init__.py
shinymap/www/shinymap-shiny.js
shinymap/www/shinymap.global.js
shinymap-0.2.1.dist-info/METADATA
shinymap-0.2.1.dist-info/WHEEL
shinymap-0.2.1.dist-info/RECORD
