Metadata-Version: 2.4
Name: shinymap
Version: 0.2.1
Summary: Interactive SVG map components for Shiny for Python
Project-URL: Homepage, https://github.com/kenjisato/shinymap
Author: shinymap contributors
License: MIT
Keywords: interactive,maps,shiny,svg,visualization
Classifier: Development Status :: 3 - Alpha
Classifier: Intended Audience :: Developers
Classifier: License :: OSI Approved :: MIT License
Classifier: Programming Language :: Python :: 3
Classifier: Programming Language :: Python :: 3.12
Classifier: Topic :: Scientific/Engineering :: Visualization
Requires-Python: >=3.12
Requires-Dist: shiny>=1.4.0
Requires-Dist: svg-py<2.0.0,>=1.9.0
Provides-Extra: demo
Requires-Dist: shiny-querynav>=0.1.0; extra == 'demo'
